easy_tpp/__init__.py
easy_tpp/torch_wrapper.py
easy_tpp/config_factory/__init__.py
easy_tpp/config_factory/config.py
easy_tpp/config_factory/data_config.py
easy_tpp/config_factory/hpo_config.py
easy_tpp/config_factory/model_config.py
easy_tpp/config_factory/runner_config.py
easy_tpp/default_registers/__init__.py
easy_tpp/default_registers/register_metrics.py
easy_tpp/default_registers/register_optuna_trials.py
easy_tpp/hpo/__init__.py
easy_tpp/hpo/base_hpo.py
easy_tpp/hpo/optuna_hpo.py
easy_tpp/model/__init__.py
easy_tpp/model/torch_model/__init__.py
easy_tpp/model/torch_model/torch_anhn.py
easy_tpp/model/torch_model/torch_attnhp.py
easy_tpp/model/torch_model/torch_baselayer.py
easy_tpp/model/torch_model/torch_basemodel.py
easy_tpp/model/torch_model/torch_fullynn.py
easy_tpp/model/torch_model/torch_intensity_free.py
easy_tpp/model/torch_model/torch_nhp.py
easy_tpp/model/torch_model/torch_ode_tpp.py
easy_tpp/model/torch_model/torch_rmtpp.py
easy_tpp/model/torch_model/torch_s2p2.py
easy_tpp/model/torch_model/torch_sahp.py
easy_tpp/model/torch_model/torch_thinning.py
easy_tpp/model/torch_model/torch_thp.py
easy_tpp/preprocess/__init__.py
easy_tpp/preprocess/data_collator.py
easy_tpp/preprocess/data_loader.py
easy_tpp/preprocess/dataset.py
easy_tpp/preprocess/event_tokenizer.py
easy_tpp/runner/__init__.py
easy_tpp/runner/base_runner.py
easy_tpp/runner/tpp_runner.py
easy_tpp/ssm/__init__.py
easy_tpp/ssm/initializers.py
easy_tpp/ssm/models.py
easy_tpp/ssm/ssm_util.py
easy_tpp/utils/__init__.py
easy_tpp/utils/const.py
easy_tpp/utils/gen_utils.py
easy_tpp/utils/generic.py
easy_tpp/utils/import_utils.py
easy_tpp/utils/log_utils.py
easy_tpp/utils/metrics.py
easy_tpp/utils/misc.py
easy_tpp/utils/multiprocess_utils.py
easy_tpp/utils/ode_utils.py
easy_tpp/utils/registrable.py
easy_tpp/utils/torch_utils.py
easy_tpp-0.2.1.dist-info/licenses/LICENCE
easy_tpp-0.2.1.dist-info/licenses/NOTICE
easy_tpp-0.2.1.dist-info/METADATA
easy_tpp-0.2.1.dist-info/WHEEL
easy_tpp-0.2.1.dist-info/top_level.txt
easy_tpp-0.2.1.dist-info/RECORD
