Metadata-Version: 2.4
Name: easy_tpp
Version: 0.2.1
Summary: An easy and flexible tool for neural temporal point process
Home-page: https://github.com/ant-research/EasyTemporalPointProcess/
Author: Alipay
Classifier: Programming Language :: Python :: 3
License-File: LICENCE
License-File: NOTICE
Requires-Dist: PyYAML>=5.1
Requires-Dist: numpy
Requires-Dist: pandas
Requires-Dist: torch
Requires-Dist: tensorboard
Requires-Dist: packaging
Requires-Dist: datasets
Requires-Dist: omegaconf
Dynamic: author
Dynamic: classifier
Dynamic: home-page
Dynamic: license-file
Dynamic: requires-dist
Dynamic: summary
